Metadata-Version: 2.1
Name: aioeachlimit
Version: 0.1.0
Summary: Apply an async function to each item in an array or queue with limited concurrency
Home-page: http://github.com/dflupu/aioeachlimit
Author: Daniel Lupu
Author-email: dflupu@gmail.com
License: MIT
Keywords: asyncio aio each limit concurrency generator synchronization
Platform: UNKNOWN
